{
  "date": "2026-04-10",
  "scan_time": "2026-04-10 15:24:18",
  "exchange": "Upbit",
  "market": "KRW",
  "timeframes": [
    "1D",
    "4H"
  ],
  "total_scanned": 200,
  "strong_buy_count": 3,
  "buy_count": 18,
  "watch_count": 20,
  "dual_strong_count": 1,
  "buy_targets_count": 0,
  "top_signals": [
    {
      "symbol": "KRW-JST",
      "current_price": 104.0,
      "signal": "STRONG BUY",
      "score": 8,
      "max_score": 9,
      "ma60": 78.04,
      "jongi_gap": 0.67,
      "jongi_gap_trend": "증가",
      "cycle_zone": "2번",
      "cycle_label": "📈 상승가속",
      "macd_signal": "영선위",
      "obv_signal": "상승중",
      "volume_signal": "감소",
      "cloud_status": "구름대위_양운",
      "bb_position": 115.2,
      "price_vs_ma60_pct": 31.98,
      "satisfied_conditions": [
        "현재가_MA60_위",
        "MA60_우상향",
        "종이격_증가중",
        "MACD_영선_위",
        "OBV_상승중",
        "정배열_전환선_10이평_기준선",
        "구름대_위_및_양운",
        "1D_신고가_발생"
      ],
      "tf_4h": {
        "signal": "STRONG BUY",
        "score": 9,
        "cycle_zone": "2번",
        "cycle_label": "📈 상승가속",
        "jongi_gap": 0.2233,
        "macd_signal": "영선위",
        "obv_signal": "상승중",
        "satisfied_conditions": [
          "현재가_MA60_위",
          "MA60_우상향",
          "종이격_증가중",
          "MACD_영선_위",
          "OBV_상승중",
          "거래량_증가",
          "정배열_전환선_10이평_기준선",
          "구름대_위_및_양운",
          "4H_신고가_발생"
        ],
        "jongi_gaps": [
          0.16500000000000625,
          0.18833333333331836,
          0.20500000000002672,
          0.22333333333332916
        ]
      },
      "dual_strong": true
    },
    {
      "symbol": "KRW-DKA",
      "current_price": 9.02,
      "signal": "STRONG BUY",
      "score": 8,
      "max_score": 9,
      "ma60": 7.43,
      "jongi_gap": 0.03,
      "jongi_gap_trend": "증가",
      "cycle_zone": "2번",
      "cycle_label": "📈 상승가속",
      "macd_signal": "영선위",
      "obv_signal": "상승중",
      "volume_signal": "감소",
      "cloud_status": "구름대위_양운",
      "bb_position": 105.4,
      "price_vs_ma60_pct": 23.81,
      "satisfied_conditions": [
        "현재가_MA60_위",
        "MA60_우상향",
        "종이격_증가중",
        "MACD_영선_위",
        "OBV_상승중",
        "정배열_전환선_10이평_기준선",
        "구름대_위_및_양운",
        "1D_신고가_발생"
      ],
      "tf_4h": {
        "signal": "BUY",
        "score": 6,
        "cycle_zone": "2번",
        "cycle_label": "📈 상승가속",
        "jongi_gap": 0.0195,
        "macd_signal": "영선위",
        "obv_signal": "상승중",
        "satisfied_conditions": [
          "현재가_MA60_위",
          "MA60_우상향",
          "종이격_증가중",
          "MACD_영선_위",
          "OBV_상승중",
          "정배열_전환선_10이평_기준선"
        ],
        "jongi_gaps": [
          0.019166666666666998,
          0.020666666666667055,
          0.019166666666665222,
          0.01950000000000074
        ]
      },
      "dual_strong": false
    },
    {
      "symbol": "KRW-SAFE",
      "current_price": 194.0,
      "signal": "STRONG BUY",
      "score": 8,
      "max_score": 9,
      "ma60": 157.45,
      "jongi_gap": 0.7,
      "jongi_gap_trend": "증가",
      "cycle_zone": "2번",
      "cycle_label": "📈 상승가속",
      "macd_signal": "영선위",
      "obv_signal": "상승중",
      "volume_signal": "증가",
      "cloud_status": "구름대아래",
      "bb_position": 105.2,
      "price_vs_ma60_pct": 22.58,
      "satisfied_conditions": [
        "현재가_MA60_위",
        "MA60_우상향",
        "종이격_증가중",
        "MACD_영선_위",
        "OBV_상승중",
        "거래량_증가",
        "정배열_전환선_10이평_기준선",
        "1D_신고가_발생"
      ],
      "tf_4h": {
        "signal": "BUY",
        "score": 6,
        "cycle_zone": "4번",
        "cycle_label": "⚠️ 상승둔화",
        "jongi_gap": 0.8167,
        "macd_signal": "영선위",
        "obv_signal": "상승중",
        "satisfied_conditions": [
          "현재가_MA60_위",
          "MA60_우상향",
          "MACD_영선_위",
          "OBV_상승중",
          "정배열_전환선_10이평_기준선",
          "구름대_위_및_양운"
        ],
        "jongi_gaps": [
          0.7666666666666515,
          0.9166666666666856,
          0.8333333333333144,
          0.8166666666666629
        ]
      },
      "dual_strong": false
    },
    {
      "symbol": "KRW-KAITO",
      "current_price": 575.0,
      "signal": "BUY",
      "score": 7,
      "max_score": 9,
      "ma60": 532.9,
      "jongi_gap": 2.33,
      "jongi_gap_trend": "감소",
      "cycle_zone": "3번",
      "cycle_label": "⚡ 45도 피크",
      "macd_signal": "영선위",
      "obv_signal": "상승중",
      "volume_signal": "증가",
      "cloud_status": "구름대위_양운",
      "bb_position": 47.9,
      "price_vs_ma60_pct": 13.72,
      "satisfied_conditions": [
        "현재가_MA60_위",
        "MA60_우상향",
        "MACD_영선_위",
        "OBV_상승중",
        "거래량_증가",
        "정배열_전환선_10이평_기준선",
        "구름대_위_및_양운"
      ],
      "tf_4h": {
        "signal": null,
        "score": null,
        "cycle_zone": null,
        "cycle_label": null,
        "jongi_gap": null,
        "macd_signal": null,
        "obv_signal": null,
        "satisfied_conditions": [],
        "jongi_gaps": []
      },
      "dual_strong": false
    },
    {
      "symbol": "KRW-ALGO",
      "current_price": 165.0,
      "signal": "BUY",
      "score": 7,
      "max_score": 9,
      "ma60": 137.48,
      "jongi_gap": 0.4,
      "jongi_gap_trend": "감소",
      "cycle_zone": "4번",
      "cycle_label": "⚠️ 상승둔화",
      "macd_signal": "영선위",
      "obv_signal": "상승중",
      "volume_signal": "증가",
      "cloud_status": "구름대위_양운",
      "bb_position": 69.3,
      "price_vs_ma60_pct": 21.47,
      "satisfied_conditions": [
        "현재가_MA60_위",
        "MA60_우상향",
        "MACD_영선_위",
        "OBV_상승중",
        "거래량_증가",
        "정배열_전환선_10이평_기준선",
        "구름대_위_및_양운"
      ],
      "tf_4h": {
        "signal": null,
        "score": null,
        "cycle_zone": null,
        "cycle_label": null,
        "jongi_gap": null,
        "macd_signal": null,
        "obv_signal": null,
        "satisfied_conditions": [],
        "jongi_gaps": []
      },
      "dual_strong": false
    },
    {
      "symbol": "KRW-AGLD",
      "current_price": 380.0,
      "signal": "BUY",
      "score": 7,
      "max_score": 9,
      "ma60": 364.1,
      "jongi_gap": 1.05,
      "jongi_gap_trend": "증가",
      "cycle_zone": "2번",
      "cycle_label": "📈 상승가속",
      "macd_signal": "영선위",
      "obv_signal": "상승중",
      "volume_signal": "증가",
      "cloud_status": "구름대아래",
      "bb_position": 108.8,
      "price_vs_ma60_pct": 5.19,
      "satisfied_conditions": [
        "현재가_MA60_위",
        "MA60_우상향",
        "종이격_증가중",
        "MACD_영선_위",
        "OBV_상승중",
        "거래량_증가",
        "정배열_전환선_10이평_기준선"
      ],
      "tf_4h": {
        "signal": "BUY",
        "score": 6,
        "cycle_zone": "4번",
        "cycle_label": "⚠️ 상승둔화",
        "jongi_gap": 0.4833,
        "macd_signal": "영선위",
        "obv_signal": "상승중",
        "satisfied_conditions": [
          "현재가_MA60_위",
          "MA60_우상향",
          "MACD_영선_위",
          "OBV_상승중",
          "정배열_전환선_10이평_기준선",
          "구름대_위_및_양운"
        ],
        "jongi_gaps": [
          0.5833333333333712,
          0.6833333333333371,
          0.5499999999999545,
          0.4833333333333485
        ]
      },
      "dual_strong": false
    },
    {
      "symbol": "KRW-BLUR",
      "current_price": 32.7,
      "signal": "BUY",
      "score": 7,
      "max_score": 9,
      "ma60": 29.18,
      "jongi_gap": 0.05,
      "jongi_gap_trend": "증가",
      "cycle_zone": "1번",
      "cycle_label": "🚀 상승전환",
      "macd_signal": "영선위",
      "obv_signal": "상승중",
      "volume_signal": "증가",
      "cloud_status": "구름대아래",
      "bb_position": 100.0,
      "price_vs_ma60_pct": 13.07,
      "satisfied_conditions": [
        "현재가_MA60_위",
        "MA60_우상향",
        "종이격_증가중",
        "MACD_영선_위",
        "OBV_상승중",
        "거래량_증가",
        "정배열_전환선_10이평_기준선"
      ],
      "tf_4h": {
        "signal": "WATCH",
        "score": 5,
        "cycle_zone": "4번",
        "cycle_label": "⚠️ 상승둔화",
        "jongi_gap": 0.1033,
        "macd_signal": "영선위",
        "obv_signal": "하락중",
        "satisfied_conditions": [
          "현재가_MA60_위",
          "MA60_우상향",
          "MACD_영선_위",
          "거래량_증가",
          "정배열_전환선_10이평_기준선"
        ],
        "jongi_gaps": [
          0.14000000000000412,
          0.134999999999998,
          0.11666666666666714,
          0.10333333333333172
        ]
      },
      "dual_strong": false
    },
    {
      "symbol": "KRW-ORDER",
      "current_price": 94.4,
      "signal": "BUY",
      "score": 7,
      "max_score": 9,
      "ma60": 81.14,
      "jongi_gap": 0.13,
      "jongi_gap_trend": "증가",
      "cycle_zone": "2번",
      "cycle_label": "📈 상승가속",
      "macd_signal": "영선위",
      "obv_signal": "상승중",
      "volume_signal": "증가",
      "cloud_status": "구름대아래",
      "bb_position": 94.8,
      "price_vs_ma60_pct": 14.0,
      "satisfied_conditions": [
        "현재가_MA60_위",
        "MA60_우상향",
        "종이격_증가중",
        "MACD_영선_위",
        "OBV_상승중",
        "거래량_증가",
        "1D_신고가_발생"
      ],
      "tf_4h": {
        "signal": "BUY",
        "score": 6,
        "cycle_zone": "2번",
        "cycle_label": "📈 상승가속",
        "jongi_gap": 0.425,
        "macd_signal": "영선위",
        "obv_signal": "하락중",
        "satisfied_conditions": [
          "현재가_MA60_위",
          "MA60_우상향",
          "종이격_증가중",
          "MACD_영선_위",
          "구름대_위_및_양운",
          "4H_신고가_발생"
        ],
        "jongi_gaps": [
          0.298333333333332,
          0.3366666666666589,
          0.32833333333334735,
          0.42499999999999716
        ]
      },
      "dual_strong": false
    },
    {
      "symbol": "KRW-OPEN",
      "current_price": 271.0,
      "signal": "BUY",
      "score": 7,
      "max_score": 9,
      "ma60": 235.9,
      "jongi_gap": 0.72,
      "jongi_gap_trend": "증가",
      "cycle_zone": "2번",
      "cycle_label": "📈 상승가속",
      "macd_signal": "영선위",
      "obv_signal": "상승중",
      "volume_signal": "증가",
      "cloud_status": "구름대위_음운",
      "bb_position": 102.3,
      "price_vs_ma60_pct": 17.0,
      "satisfied_conditions": [
        "현재가_MA60_위",
        "MA60_우상향",
        "종이격_증가중",
        "MACD_영선_위",
        "OBV_상승중",
        "거래량_증가",
        "정배열_전환선_10이평_기준선"
      ],
      "tf_4h": {
        "signal": "BUY",
        "score": 6,
        "cycle_zone": "4번",
        "cycle_label": "⚠️ 상승둔화",
        "jongi_gap": 0.5667,
        "macd_signal": "영선위",
        "obv_signal": "상승중",
        "satisfied_conditions": [
          "현재가_MA60_위",
          "MA60_우상향",
          "MACD_영선_위",
          "OBV_상승중",
          "정배열_전환선_10이평_기준선",
          "4H_신고가_발생"
        ],
        "jongi_gaps": [
          0.5333333333333314,
          0.6666666666666572,
          0.6500000000000057,
          0.5666666666666629
        ]
      },
      "dual_strong": false
    },
    {
      "symbol": "KRW-RENDER",
      "current_price": 3043.0,
      "signal": "BUY",
      "score": 7,
      "max_score": 9,
      "ma60": 2365.42,
      "jongi_gap": 16.97,
      "jongi_gap_trend": "증가",
      "cycle_zone": "2번",
      "cycle_label": "📈 상승가속",
      "macd_signal": "영선위",
      "obv_signal": "상승중",
      "volume_signal": "감소",
      "cloud_status": "구름대위_양운",
      "bb_position": 89.6,
      "price_vs_ma60_pct": 27.67,
      "satisfied_conditions": [
        "현재가_MA60_위",
        "MA60_우상향",
        "종이격_증가중",
        "MACD_영선_위",
        "OBV_상승중",
        "정배열_전환선_10이평_기준선",
        "구름대_위_및_양운"
      ],
      "tf_4h": {
        "signal": "WATCH",
        "score": 5,
        "cycle_zone": "4번",
        "cycle_label": "⚠️ 상승둔화",
        "jongi_gap": 6.6,
        "macd_signal": "영선위",
        "obv_signal": "상승중",
        "satisfied_conditions": [
          "현재가_MA60_위",
          "MA60_우상향",
          "MACD_영선_위",
          "OBV_상승중",
          "구름대_위_및_양운"
        ],
        "jongi_gaps": [
          7.716666666666697,
          7.983333333333121,
          7.733333333333576,
          6.599999999999909
        ]
      },
      "dual_strong": false
    }
  ],
  "all_buy_signals": [
    {
      "symbol": "KRW-JST",
      "current_price": 104.0,
      "signal": "STRONG BUY",
      "score": 8,
      "max_score": 9,
      "ma60": 78.04,
      "jongi_gap": 0.67,
      "jongi_gap_trend": "증가",
      "cycle_zone": "2번",
      "cycle_label": "📈 상승가속",
      "macd_signal": "영선위",
      "obv_signal": "상승중",
      "volume_signal": "감소",
      "cloud_status": "구름대위_양운",
      "bb_position": 115.2,
      "price_vs_ma60_pct": 31.98,
      "satisfied_conditions": [
        "현재가_MA60_위",
        "MA60_우상향",
        "종이격_증가중",
        "MACD_영선_위",
        "OBV_상승중",
        "정배열_전환선_10이평_기준선",
        "구름대_위_및_양운",
        "1D_신고가_발생"
      ],
      "tf_4h": {
        "signal": "STRONG BUY",
        "score": 9,
        "cycle_zone": "2번",
        "cycle_label": "📈 상승가속",
        "jongi_gap": 0.2233,
        "macd_signal": "영선위",
        "obv_signal": "상승중",
        "satisfied_conditions": [
          "현재가_MA60_위",
          "MA60_우상향",
          "종이격_증가중",
          "MACD_영선_위",
          "OBV_상승중",
          "거래량_증가",
          "정배열_전환선_10이평_기준선",
          "구름대_위_및_양운",
          "4H_신고가_발생"
        ],
        "jongi_gaps": [
          0.16500000000000625,
          0.18833333333331836,
          0.20500000000002672,
          0.22333333333332916
        ]
      },
      "dual_strong": true
    },
    {
      "symbol": "KRW-DKA",
      "current_price": 9.02,
      "signal": "STRONG BUY",
      "score": 8,
      "max_score": 9,
      "ma60": 7.43,
      "jongi_gap": 0.03,
      "jongi_gap_trend": "증가",
      "cycle_zone": "2번",
      "cycle_label": "📈 상승가속",
      "macd_signal": "영선위",
      "obv_signal": "상승중",
      "volume_signal": "감소",
      "cloud_status": "구름대위_양운",
      "bb_position": 105.4,
      "price_vs_ma60_pct": 23.81,
      "satisfied_conditions": [
        "현재가_MA60_위",
        "MA60_우상향",
        "종이격_증가중",
        "MACD_영선_위",
        "OBV_상승중",
        "정배열_전환선_10이평_기준선",
        "구름대_위_및_양운",
        "1D_신고가_발생"
      ],
      "tf_4h": {
        "signal": "BUY",
        "score": 6,
        "cycle_zone": "2번",
        "cycle_label": "📈 상승가속",
        "jongi_gap": 0.0195,
        "macd_signal": "영선위",
        "obv_signal": "상승중",
        "satisfied_conditions": [
          "현재가_MA60_위",
          "MA60_우상향",
          "종이격_증가중",
          "MACD_영선_위",
          "OBV_상승중",
          "정배열_전환선_10이평_기준선"
        ],
        "jongi_gaps": [
          0.019166666666666998,
          0.020666666666667055,
          0.019166666666665222,
          0.01950000000000074
        ]
      },
      "dual_strong": false
    },
    {
      "symbol": "KRW-SAFE",
      "current_price": 194.0,
      "signal": "STRONG BUY",
      "score": 8,
      "max_score": 9,
      "ma60": 157.45,
      "jongi_gap": 0.7,
      "jongi_gap_trend": "증가",
      "cycle_zone": "2번",
      "cycle_label": "📈 상승가속",
      "macd_signal": "영선위",
      "obv_signal": "상승중",
      "volume_signal": "증가",
      "cloud_status": "구름대아래",
      "bb_position": 105.2,
      "price_vs_ma60_pct": 22.58,
      "satisfied_conditions": [
        "현재가_MA60_위",
        "MA60_우상향",
        "종이격_증가중",
        "MACD_영선_위",
        "OBV_상승중",
        "거래량_증가",
        "정배열_전환선_10이평_기준선",
        "1D_신고가_발생"
      ],
      "tf_4h": {
        "signal": "BUY",
        "score": 6,
        "cycle_zone": "4번",
        "cycle_label": "⚠️ 상승둔화",
        "jongi_gap": 0.8167,
        "macd_signal": "영선위",
        "obv_signal": "상승중",
        "satisfied_conditions": [
          "현재가_MA60_위",
          "MA60_우상향",
          "MACD_영선_위",
          "OBV_상승중",
          "정배열_전환선_10이평_기준선",
          "구름대_위_및_양운"
        ],
        "jongi_gaps": [
          0.7666666666666515,
          0.9166666666666856,
          0.8333333333333144,
          0.8166666666666629
        ]
      },
      "dual_strong": false
    },
    {
      "symbol": "KRW-KAITO",
      "current_price": 575.0,
      "signal": "BUY",
      "score": 7,
      "max_score": 9,
      "ma60": 532.9,
      "jongi_gap": 2.33,
      "jongi_gap_trend": "감소",
      "cycle_zone": "3번",
      "cycle_label": "⚡ 45도 피크",
      "macd_signal": "영선위",
      "obv_signal": "상승중",
      "volume_signal": "증가",
      "cloud_status": "구름대위_양운",
      "bb_position": 47.9,
      "price_vs_ma60_pct": 13.72,
      "satisfied_conditions": [
        "현재가_MA60_위",
        "MA60_우상향",
        "MACD_영선_위",
        "OBV_상승중",
        "거래량_증가",
        "정배열_전환선_10이평_기준선",
        "구름대_위_및_양운"
      ],
      "tf_4h": {
        "signal": null,
        "score": null,
        "cycle_zone": null,
        "cycle_label": null,
        "jongi_gap": null,
        "macd_signal": null,
        "obv_signal": null,
        "satisfied_conditions": [],
        "jongi_gaps": []
      },
      "dual_strong": false
    },
    {
      "symbol": "KRW-ALGO",
      "current_price": 165.0,
      "signal": "BUY",
      "score": 7,
      "max_score": 9,
      "ma60": 137.48,
      "jongi_gap": 0.4,
      "jongi_gap_trend": "감소",
      "cycle_zone": "4번",
      "cycle_label": "⚠️ 상승둔화",
      "macd_signal": "영선위",
      "obv_signal": "상승중",
      "volume_signal": "증가",
      "cloud_status": "구름대위_양운",
      "bb_position": 69.3,
      "price_vs_ma60_pct": 21.47,
      "satisfied_conditions": [
        "현재가_MA60_위",
        "MA60_우상향",
        "MACD_영선_위",
        "OBV_상승중",
        "거래량_증가",
        "정배열_전환선_10이평_기준선",
        "구름대_위_및_양운"
      ],
      "tf_4h": {
        "signal": null,
        "score": null,
        "cycle_zone": null,
        "cycle_label": null,
        "jongi_gap": null,
        "macd_signal": null,
        "obv_signal": null,
        "satisfied_conditions": [],
        "jongi_gaps": []
      },
      "dual_strong": false
    },
    {
      "symbol": "KRW-AGLD",
      "current_price": 380.0,
      "signal": "BUY",
      "score": 7,
      "max_score": 9,
      "ma60": 364.1,
      "jongi_gap": 1.05,
      "jongi_gap_trend": "증가",
      "cycle_zone": "2번",
      "cycle_label": "📈 상승가속",
      "macd_signal": "영선위",
      "obv_signal": "상승중",
      "volume_signal": "증가",
      "cloud_status": "구름대아래",
      "bb_position": 108.8,
      "price_vs_ma60_pct": 5.19,
      "satisfied_conditions": [
        "현재가_MA60_위",
        "MA60_우상향",
        "종이격_증가중",
        "MACD_영선_위",
        "OBV_상승중",
        "거래량_증가",
        "정배열_전환선_10이평_기준선"
      ],
      "tf_4h": {
        "signal": "BUY",
        "score": 6,
        "cycle_zone": "4번",
        "cycle_label": "⚠️ 상승둔화",
        "jongi_gap": 0.4833,
        "macd_signal": "영선위",
        "obv_signal": "상승중",
        "satisfied_conditions": [
          "현재가_MA60_위",
          "MA60_우상향",
          "MACD_영선_위",
          "OBV_상승중",
          "정배열_전환선_10이평_기준선",
          "구름대_위_및_양운"
        ],
        "jongi_gaps": [
          0.5833333333333712,
          0.6833333333333371,
          0.5499999999999545,
          0.4833333333333485
        ]
      },
      "dual_strong": false
    },
    {
      "symbol": "KRW-BLUR",
      "current_price": 32.7,
      "signal": "BUY",
      "score": 7,
      "max_score": 9,
      "ma60": 29.18,
      "jongi_gap": 0.05,
      "jongi_gap_trend": "증가",
      "cycle_zone": "1번",
      "cycle_label": "🚀 상승전환",
      "macd_signal": "영선위",
      "obv_signal": "상승중",
      "volume_signal": "증가",
      "cloud_status": "구름대아래",
      "bb_position": 100.0,
      "price_vs_ma60_pct": 13.07,
      "satisfied_conditions": [
        "현재가_MA60_위",
        "MA60_우상향",
        "종이격_증가중",
        "MACD_영선_위",
        "OBV_상승중",
        "거래량_증가",
        "정배열_전환선_10이평_기준선"
      ],
      "tf_4h": {
        "signal": "WATCH",
        "score": 5,
        "cycle_zone": "4번",
        "cycle_label": "⚠️ 상승둔화",
        "jongi_gap": 0.1033,
        "macd_signal": "영선위",
        "obv_signal": "하락중",
        "satisfied_conditions": [
          "현재가_MA60_위",
          "MA60_우상향",
          "MACD_영선_위",
          "거래량_증가",
          "정배열_전환선_10이평_기준선"
        ],
        "jongi_gaps": [
          0.14000000000000412,
          0.134999999999998,
          0.11666666666666714,
          0.10333333333333172
        ]
      },
      "dual_strong": false
    },
    {
      "symbol": "KRW-ORDER",
      "current_price": 94.4,
      "signal": "BUY",
      "score": 7,
      "max_score": 9,
      "ma60": 81.14,
      "jongi_gap": 0.13,
      "jongi_gap_trend": "증가",
      "cycle_zone": "2번",
      "cycle_label": "📈 상승가속",
      "macd_signal": "영선위",
      "obv_signal": "상승중",
      "volume_signal": "증가",
      "cloud_status": "구름대아래",
      "bb_position": 94.8,
      "price_vs_ma60_pct": 14.0,
      "satisfied_conditions": [
        "현재가_MA60_위",
        "MA60_우상향",
        "종이격_증가중",
        "MACD_영선_위",
        "OBV_상승중",
        "거래량_증가",
        "1D_신고가_발생"
      ],
      "tf_4h": {
        "signal": "BUY",
        "score": 6,
        "cycle_zone": "2번",
        "cycle_label": "📈 상승가속",
        "jongi_gap": 0.425,
        "macd_signal": "영선위",
        "obv_signal": "하락중",
        "satisfied_conditions": [
          "현재가_MA60_위",
          "MA60_우상향",
          "종이격_증가중",
          "MACD_영선_위",
          "구름대_위_및_양운",
          "4H_신고가_발생"
        ],
        "jongi_gaps": [
          0.298333333333332,
          0.3366666666666589,
          0.32833333333334735,
          0.42499999999999716
        ]
      },
      "dual_strong": false
    },
    {
      "symbol": "KRW-OPEN",
      "current_price": 271.0,
      "signal": "BUY",
      "score": 7,
      "max_score": 9,
      "ma60": 235.9,
      "jongi_gap": 0.72,
      "jongi_gap_trend": "증가",
      "cycle_zone": "2번",
      "cycle_label": "📈 상승가속",
      "macd_signal": "영선위",
      "obv_signal": "상승중",
      "volume_signal": "증가",
      "cloud_status": "구름대위_음운",
      "bb_position": 102.3,
      "price_vs_ma60_pct": 17.0,
      "satisfied_conditions": [
        "현재가_MA60_위",
        "MA60_우상향",
        "종이격_증가중",
        "MACD_영선_위",
        "OBV_상승중",
        "거래량_증가",
        "정배열_전환선_10이평_기준선"
      ],
      "tf_4h": {
        "signal": "BUY",
        "score": 6,
        "cycle_zone": "4번",
        "cycle_label": "⚠️ 상승둔화",
        "jongi_gap": 0.5667,
        "macd_signal": "영선위",
        "obv_signal": "상승중",
        "satisfied_conditions": [
          "현재가_MA60_위",
          "MA60_우상향",
          "MACD_영선_위",
          "OBV_상승중",
          "정배열_전환선_10이평_기준선",
          "4H_신고가_발생"
        ],
        "jongi_gaps": [
          0.5333333333333314,
          0.6666666666666572,
          0.6500000000000057,
          0.5666666666666629
        ]
      },
      "dual_strong": false
    },
    {
      "symbol": "KRW-RENDER",
      "current_price": 3043.0,
      "signal": "BUY",
      "score": 7,
      "max_score": 9,
      "ma60": 2365.42,
      "jongi_gap": 16.97,
      "jongi_gap_trend": "증가",
      "cycle_zone": "2번",
      "cycle_label": "📈 상승가속",
      "macd_signal": "영선위",
      "obv_signal": "상승중",
      "volume_signal": "감소",
      "cloud_status": "구름대위_양운",
      "bb_position": 89.6,
      "price_vs_ma60_pct": 27.67,
      "satisfied_conditions": [
        "현재가_MA60_위",
        "MA60_우상향",
        "종이격_증가중",
        "MACD_영선_위",
        "OBV_상승중",
        "정배열_전환선_10이평_기준선",
        "구름대_위_및_양운"
      ],
      "tf_4h": {
        "signal": "WATCH",
        "score": 5,
        "cycle_zone": "4번",
        "cycle_label": "⚠️ 상승둔화",
        "jongi_gap": 6.6,
        "macd_signal": "영선위",
        "obv_signal": "상승중",
        "satisfied_conditions": [
          "현재가_MA60_위",
          "MA60_우상향",
          "MACD_영선_위",
          "OBV_상승중",
          "구름대_위_및_양운"
        ],
        "jongi_gaps": [
          7.716666666666697,
          7.983333333333121,
          7.733333333333576,
          6.599999999999909
        ]
      },
      "dual_strong": false
    },
    {
      "symbol": "KRW-2Z",
      "current_price": 120.0,
      "signal": "BUY",
      "score": 6,
      "max_score": 9,
      "ma60": 114.0,
      "jongi_gap": -0.22,
      "jongi_gap_trend": "증가",
      "cycle_zone": "7번",
      "cycle_label": "🔄 하락피크",
      "macd_signal": "영선위",
      "obv_signal": "상승중",
      "volume_signal": "증가",
      "cloud_status": "구름대아래",
      "bb_position": 58.6,
      "price_vs_ma60_pct": 4.39,
      "satisfied_conditions": [
        "현재가_MA60_위",
        "종이격_증가중",
        "MACD_영선_위",
        "OBV_상승중",
        "거래량_증가",
        "정배열_전환선_10이평_기준선"
      ],
      "tf_4h": {
        "signal": null,
        "score": null,
        "cycle_zone": null,
        "cycle_label": null,
        "jongi_gap": null,
        "macd_signal": null,
        "obv_signal": null,
        "satisfied_conditions": [],
        "jongi_gaps": []
      },
      "dual_strong": false
    },
    {
      "symbol": "KRW-ANKR",
      "current_price": 7.94,
      "signal": "BUY",
      "score": 6,
      "max_score": 9,
      "ma60": 6.95,
      "jongi_gap": 0.02,
      "jongi_gap_trend": "증가",
      "cycle_zone": "2번",
      "cycle_label": "📈 상승가속",
      "macd_signal": "영선위",
      "obv_signal": "상승중",
      "volume_signal": "감소",
      "cloud_status": "구름대아래",
      "bb_position": 70.0,
      "price_vs_ma60_pct": 14.46,
      "satisfied_conditions": [
        "현재가_MA60_위",
        "MA60_우상향",
        "종이격_증가중",
        "MACD_영선_위",
        "OBV_상승중",
        "정배열_전환선_10이평_기준선"
      ],
      "tf_4h": {
        "signal": "BUY",
        "score": 7,
        "cycle_zone": "2번",
        "cycle_label": "📈 상승가속",
        "jongi_gap": 0.0052,
        "macd_signal": "영선위",
        "obv_signal": "상승중",
        "satisfied_conditions": [
          "현재가_MA60_위",
          "MA60_우상향",
          "종이격_증가중",
          "MACD_영선_위",
          "OBV_상승중",
          "정배열_전환선_10이평_기준선",
          "구름대_위_및_양운"
        ],
        "jongi_gaps": [
          0.00416666666666643,
          0.005666666666667375,
          0.0014999999999982805,
          0.005166666666666764
        ]
      },
      "dual_strong": false
    },
    {
      "symbol": "KRW-JUP",
      "current_price": 239.0,
      "signal": "BUY",
      "score": 6,
      "max_score": 9,
      "ma60": 236.23,
      "jongi_gap": 0.05,
      "jongi_gap_trend": "증가",
      "cycle_zone": "1번",
      "cycle_label": "🚀 상승전환",
      "macd_signal": "영선위",
      "obv_signal": "상승중",
      "volume_signal": "감소",
      "cloud_status": "구름대아래",
      "bb_position": 63.2,
      "price_vs_ma60_pct": 1.59,
      "satisfied_conditions": [
        "현재가_MA60_위",
        "MA60_우상향",
        "종이격_증가중",
        "MACD_영선_위",
        "OBV_상승중",
        "정배열_전환선_10이평_기준선"
      ],
      "tf_4h": {
        "signal": null,
        "score": null,
        "cycle_zone": null,
        "cycle_label": null,
        "jongi_gap": null,
        "macd_signal": null,
        "obv_signal": null,
        "satisfied_conditions": [],
        "jongi_gaps": []
      },
      "dual_strong": false
    },
    {
      "symbol": "KRW-TRX",
      "current_price": 476.0,
      "signal": "BUY",
      "score": 6,
      "max_score": 9,
      "ma60": 439.9,
      "jongi_gap": 1.03,
      "jongi_gap_trend": "감소",
      "cycle_zone": "4번",
      "cycle_label": "⚠️ 상승둔화",
      "macd_signal": "영선위",
      "obv_signal": "상승중",
      "volume_signal": "감소",
      "cloud_status": "구름대위_양운",
      "bb_position": 51.8,
      "price_vs_ma60_pct": 7.98,
      "satisfied_conditions": [
        "현재가_MA60_위",
        "MA60_우상향",
        "MACD_영선_위",
        "OBV_상승중",
        "정배열_전환선_10이평_기준선",
        "구름대_위_및_양운"
      ],
      "tf_4h": {
        "signal": null,
        "score": null,
        "cycle_zone": null,
        "cycle_label": null,
        "jongi_gap": null,
        "macd_signal": null,
        "obv_signal": null,
        "satisfied_conditions": [],
        "jongi_gaps": []
      },
      "dual_strong": false
    },
    {
      "symbol": "KRW-NEO",
      "current_price": 4241.0,
      "signal": "BUY",
      "score": 6,
      "max_score": 9,
      "ma60": 3994.73,
      "jongi_gap": 0.97,
      "jongi_gap_trend": "증가",
      "cycle_zone": "1번",
      "cycle_label": "🚀 상승전환",
      "macd_signal": "영선위",
      "obv_signal": "상승중",
      "volume_signal": "감소",
      "cloud_status": "구름대아래",
      "bb_position": 59.8,
      "price_vs_ma60_pct": 3.29,
      "satisfied_conditions": [
        "현재가_MA60_위",
        "MA60_우상향",
        "종이격_증가중",
        "MACD_영선_위",
        "OBV_상승중",
        "정배열_전환선_10이평_기준선"
      ],
      "tf_4h": {
        "signal": "WATCH",
        "score": 5,
        "cycle_zone": "2번",
        "cycle_label": "📈 상승가속",
        "jongi_gap": 5.2,
        "macd_signal": "영선아래",
        "obv_signal": "상승중",
        "satisfied_conditions": [
          "현재가_MA60_위",
          "MA60_우상향",
          "종이격_증가중",
          "OBV_상승중",
          "거래량_증가"
        ],
        "jongi_gaps": [
          2.4666666666662422,
          2.933333333333394,
          1.8500000000003638,
          5.199999999999818
        ]
      },
      "dual_strong": false
    },
    {
      "symbol": "KRW-NEAR",
      "current_price": 2019.0,
      "signal": "BUY",
      "score": 6,
      "max_score": 9,
      "ma60": 1779.78,
      "jongi_gap": 8.07,
      "jongi_gap_trend": "증가",
      "cycle_zone": "2번",
      "cycle_label": "📈 상승가속",
      "macd_signal": "영선위",
      "obv_signal": "상승중",
      "volume_signal": "감소",
      "cloud_status": "구름대위_양운",
      "bb_position": 101.1,
      "price_vs_ma60_pct": 13.95,
      "satisfied_conditions": [
        "현재가_MA60_위",
        "MA60_우상향",
        "종이격_증가중",
        "MACD_영선_위",
        "OBV_상승중",
        "구름대_위_및_양운"
      ],
      "tf_4h": {
        "signal": "BUY",
        "score": 6,
        "cycle_zone": "4번",
        "cycle_label": "⚠️ 상승둔화",
        "jongi_gap": 3.6667,
        "macd_signal": "영선위",
        "obv_signal": "상승중",
        "satisfied_conditions": [
          "현재가_MA60_위",
          "MA60_우상향",
          "MACD_영선_위",
          "OBV_상승중",
          "정배열_전환선_10이평_기준선",
          "구름대_위_및_양운"
        ],
        "jongi_gaps": [
          4.2333333333333485,
          4.399999999999864,
          4.366666666666788,
          3.666666666666515
        ]
      },
      "dual_strong": false
    },
    {
      "symbol": "KRW-AQT",
      "current_price": 786.0,
      "signal": "BUY",
      "score": 6,
      "max_score": 9,
      "ma60": 761.85,
      "jongi_gap": 0.63,
      "jongi_gap_trend": "감소",
      "cycle_zone": "3번",
      "cycle_label": "⚡ 45도 피크",
      "macd_signal": "영선위",
      "obv_signal": "상승중",
      "volume_signal": "증가",
      "cloud_status": "구름대아래",
      "bb_position": 96.2,
      "price_vs_ma60_pct": 3.83,
      "satisfied_conditions": [
        "현재가_MA60_위",
        "MA60_우상향",
        "MACD_영선_위",
        "OBV_상승중",
        "거래량_증가",
        "정배열_전환선_10이평_기준선"
      ],
      "tf_4h": {
        "signal": null,
        "score": null,
        "cycle_zone": null,
        "cycle_label": null,
        "jongi_gap": null,
        "macd_signal": null,
        "obv_signal": null,
        "satisfied_conditions": [],
        "jongi_gaps": []
      },
      "dual_strong": false
    },
    {
      "symbol": "KRW-CPOOL",
      "current_price": 36.0,
      "signal": "BUY",
      "score": 6,
      "max_score": 9,
      "ma60": 31.96,
      "jongi_gap": 0.1,
      "jongi_gap_trend": "증가",
      "cycle_zone": "2번",
      "cycle_label": "📈 상승가속",
      "macd_signal": "영선위",
      "obv_signal": "상승중",
      "volume_signal": "감소",
      "cloud_status": "구름대아래",
      "bb_position": 79.8,
      "price_vs_ma60_pct": 12.96,
      "satisfied_conditions": [
        "현재가_MA60_위",
        "MA60_우상향",
        "종이격_증가중",
        "MACD_영선_위",
        "OBV_상승중",
        "정배열_전환선_10이평_기준선"
      ],
      "tf_4h": {
        "signal": "BUY",
        "score": 7,
        "cycle_zone": "2번",
        "cycle_label": "📈 상승가속",
        "jongi_gap": 0.0517,
        "macd_signal": "영선위",
        "obv_signal": "상승중",
        "satisfied_conditions": [
          "현재가_MA60_위",
          "MA60_우상향",
          "종이격_증가중",
          "MACD_영선_위",
          "OBV_상승중",
          "정배열_전환선_10이평_기준선",
          "구름대_위_및_양운"
        ],
        "jongi_gaps": [
          0.043333333333336554,
          0.04999999999999716,
          0.05166666666666231,
          0.051666666666669414
        ]
      },
      "dual_strong": false
    },
    {
      "symbol": "KRW-LINEA",
      "current_price": 4.94,
      "signal": "BUY",
      "score": 6,
      "max_score": 9,
      "ma60": 4.84,
      "jongi_gap": 0.0,
      "jongi_gap_trend": "증가",
      "cycle_zone": "1번",
      "cycle_label": "🚀 상승전환",
      "macd_signal": "영선위",
      "obv_signal": "상승중",
      "volume_signal": "감소",
      "cloud_status": "구름대아래",
      "bb_position": 71.3,
      "price_vs_ma60_pct": 1.41,
      "satisfied_conditions": [
        "현재가_MA60_위",
        "MA60_우상향",
        "종이격_증가중",
        "MACD_영선_위",
        "OBV_상승중",
        "정배열_전환선_10이평_기준선"
      ],
      "tf_4h": {
        "signal": null,
        "score": null,
        "cycle_zone": null,
        "cycle_label": null,
        "jongi_gap": null,
        "macd_signal": null,
        "obv_signal": null,
        "satisfied_conditions": [],
        "jongi_gaps": []
      },
      "dual_strong": false
    },
    {
      "symbol": "KRW-MTL",
      "current_price": 428.0,
      "signal": "BUY",
      "score": 6,
      "max_score": 9,
      "ma60": 412.0,
      "jongi_gap": 0.3,
      "jongi_gap_trend": "증가",
      "cycle_zone": "2번",
      "cycle_label": "📈 상승가속",
      "macd_signal": "영선위",
      "obv_signal": "상승중",
      "volume_signal": "감소",
      "cloud_status": "구름대아래",
      "bb_position": 67.9,
      "price_vs_ma60_pct": 3.4,
      "satisfied_conditions": [
        "현재가_MA60_위",
        "MA60_우상향",
        "종이격_증가중",
        "MACD_영선_위",
        "OBV_상승중",
        "정배열_전환선_10이평_기준선"
      ],
      "tf_4h": {
        "signal": null,
        "score": null,
        "cycle_zone": null,
        "cycle_label": null,
        "jongi_gap": null,
        "macd_signal": null,
        "obv_signal": null,
        "satisfied_conditions": [],
        "jongi_gaps": []
      },
      "dual_strong": false
    },
    {
      "symbol": "KRW-XPL",
      "current_price": 194.0,
      "signal": "BUY",
      "score": 6,
      "max_score": 9,
      "ma60": 150.0,
      "jongi_gap": 1.02,
      "jongi_gap_trend": "감소",
      "cycle_zone": "4번",
      "cycle_label": "⚠️ 상승둔화",
      "macd_signal": "영선위",
      "obv_signal": "상승중",
      "volume_signal": "증가",
      "cloud_status": "구름대위_음운",
      "bb_position": 79.9,
      "price_vs_ma60_pct": 22.0,
      "satisfied_conditions": [
        "현재가_MA60_위",
        "MA60_우상향",
        "MACD_영선_위",
        "OBV_상승중",
        "거래량_증가",
        "정배열_전환선_10이평_기준선"
      ],
      "tf_4h": {
        "signal": null,
        "score": null,
        "cycle_zone": null,
        "cycle_label": null,
        "jongi_gap": null,
        "macd_signal": null,
        "obv_signal": null,
        "satisfied_conditions": [],
        "jongi_gaps": []
      },
      "dual_strong": false
    }
  ],
  "all_watch_signals": [
    {
      "symbol": "KRW-HUNT",
      "current_price": 149.0,
      "signal": "WATCH",
      "score": 5,
      "max_score": 9,
      "ma60": 148.97,
      "jongi_gap": -0.12,
      "jongi_gap_trend": "증가",
      "cycle_zone": "7번",
      "cycle_label": "🔄 하락피크",
      "macd_signal": "영선위",
      "obv_signal": "상승중",
      "volume_signal": "감소",
      "cloud_status": "구름대아래",
      "bb_position": 69.8,
      "price_vs_ma60_pct": 1.36,
      "satisfied_conditions": [
        "현재가_MA60_위",
        "종이격_증가중",
        "MACD_영선_위",
        "OBV_상승중",
        "정배열_전환선_10이평_기준선"
      ],
      "tf_4h": {
        "signal": null,
        "score": null,
        "cycle_zone": null,
        "cycle_label": null,
        "jongi_gap": null,
        "macd_signal": null,
        "obv_signal": null,
        "satisfied_conditions": [],
        "jongi_gaps": []
      },
      "dual_strong": false
    },
    {
      "symbol": "KRW-WET",
      "current_price": 145.0,
      "signal": "WATCH",
      "score": 5,
      "max_score": 9,
      "ma60": 148.13,
      "jongi_gap": 0.65,
      "jongi_gap_trend": "증가",
      "cycle_zone": "2번",
      "cycle_label": "📈 상승가속",
      "macd_signal": "영선위",
      "obv_signal": "하락중",
      "volume_signal": "감소",
      "cloud_status": "구름대위_양운",
      "bb_position": 20.4,
      "price_vs_ma60_pct": 3.29,
      "satisfied_conditions": [
        "현재가_MA60_위",
        "MA60_우상향",
        "종이격_증가중",
        "MACD_영선_위",
        "구름대_위_및_양운"
      ],
      "tf_4h": {
        "signal": null,
        "score": null,
        "cycle_zone": null,
        "cycle_label": null,
        "jongi_gap": null,
        "macd_signal": null,
        "obv_signal": null,
        "satisfied_conditions": [],
        "jongi_gaps": []
      },
      "dual_strong": false
    },
    {
      "symbol": "KRW-POWR",
      "current_price": 98.0,
      "signal": "WATCH",
      "score": 5,
      "max_score": 9,
      "ma60": 95.0,
      "jongi_gap": -0.04,
      "jongi_gap_trend": "증가",
      "cycle_zone": "7번",
      "cycle_label": "🔄 하락피크",
      "macd_signal": "영선위",
      "obv_signal": "상승중",
      "volume_signal": "감소",
      "cloud_status": "구름대아래",
      "bb_position": 83.9,
      "price_vs_ma60_pct": 3.79,
      "satisfied_conditions": [
        "현재가_MA60_위",
        "종이격_증가중",
        "MACD_영선_위",
        "OBV_상승중",
        "정배열_전환선_10이평_기준선"
      ],
      "tf_4h": {
        "signal": "BUY",
        "score": 6,
        "cycle_zone": "4번",
        "cycle_label": "⚠️ 상승둔화",
        "jongi_gap": 0.0833,
        "macd_signal": "영선위",
        "obv_signal": "하락중",
        "satisfied_conditions": [
          "현재가_MA60_위",
          "MA60_우상향",
          "MACD_영선_위",
          "거래량_증가",
          "정배열_전환선_10이평_기준선",
          "구름대_위_및_양운"
        ],
        "jongi_gaps": [
          0.09333333333334792,
          0.12333333333332064,
          0.09666666666667822,
          0.08333333333334281
        ]
      },
      "dual_strong": false
    },
    {
      "symbol": "KRW-NXPC",
      "current_price": 428.0,
      "signal": "WATCH",
      "score": 5,
      "max_score": 9,
      "ma60": 415.68,
      "jongi_gap": 0.18,
      "jongi_gap_trend": "증가",
      "cycle_zone": "1번",
      "cycle_label": "🚀 상승전환",
      "macd_signal": "영선위",
      "obv_signal": "상승중",
      "volume_signal": "감소",
      "cloud_status": "구름대아래",
      "bb_position": 51.7,
      "price_vs_ma60_pct": 3.2,
      "satisfied_conditions": [
        "현재가_MA60_위",
        "MA60_우상향",
        "종이격_증가중",
        "MACD_영선_위",
        "OBV_상승중"
      ],
      "tf_4h": {
        "signal": null,
        "score": null,
        "cycle_zone": null,
        "cycle_label": null,
        "jongi_gap": null,
        "macd_signal": null,
        "obv_signal": null,
        "satisfied_conditions": [],
        "jongi_gaps": []
      },
      "dual_strong": false
    },
    {
      "symbol": "KRW-G",
      "current_price": 5.84,
      "signal": "WATCH",
      "score": 5,
      "max_score": 9,
      "ma60": 5.55,
      "jongi_gap": 0.0,
      "jongi_gap_trend": "증가",
      "cycle_zone": "1번",
      "cycle_label": "🚀 상승전환",
      "macd_signal": "영선위",
      "obv_signal": "상승중",
      "volume_signal": "감소",
      "cloud_status": "구름대아래",
      "bb_position": 68.4,
      "price_vs_ma60_pct": 4.06,
      "satisfied_conditions": [
        "현재가_MA60_위",
        "MA60_우상향",
        "종이격_증가중",
        "MACD_영선_위",
        "OBV_상승중"
      ],
      "tf_4h": {
        "signal": "WATCH",
        "score": 5,
        "cycle_zone": "5번",
        "cycle_label": "🔻 하락전환",
        "jongi_gap": -0.0137,
        "macd_signal": "영선위",
        "obv_signal": "상승중",
        "satisfied_conditions": [
          "현재가_MA60_위",
          "MACD_영선_위",
          "OBV_상승중",
          "거래량_증가",
          "정배열_전환선_10이평_기준선"
        ],
        "jongi_gaps": [
          0.0086666666666666,
          0.009999999999998899,
          0.00849999999999973,
          -0.013666666666665606
        ]
      },
      "dual_strong": false
    },
    {
      "symbol": "KRW-CELO",
      "current_price": 121.0,
      "signal": "WATCH",
      "score": 5,
      "max_score": 9,
      "ma60": 118.08,
      "jongi_gap": -0.08,
      "jongi_gap_trend": "감소",
      "cycle_zone": "5번",
      "cycle_label": "🔻 하락전환",
      "macd_signal": "영선위",
      "obv_signal": "상승중",
      "volume_signal": "증가",
      "cloud_status": "구름대아래",
      "bb_position": 38.4,
      "price_vs_ma60_pct": 1.62,
      "satisfied_conditions": [
        "현재가_MA60_위",
        "MACD_영선_위",
        "OBV_상승중",
        "거래량_증가",
        "정배열_전환선_10이평_기준선"
      ],
      "tf_4h": {
        "signal": null,
        "score": null,
        "cycle_zone": null,
        "cycle_label": null,
        "jongi_gap": null,
        "macd_signal": null,
        "obv_signal": null,
        "satisfied_conditions": [],
        "jongi_gaps": []
      },
      "dual_strong": false
    },
    {
      "symbol": "KRW-AERO",
      "current_price": 548.0,
      "signal": "WATCH",
      "score": 5,
      "max_score": 9,
      "ma60": 485.4,
      "jongi_gap": 0.98,
      "jongi_gap_trend": "증가",
      "cycle_zone": "2번",
      "cycle_label": "📈 상승가속",
      "macd_signal": "영선위",
      "obv_signal": "하락중",
      "volume_signal": "감소",
      "cloud_status": "구름대아래",
      "bb_position": 116.3,
      "price_vs_ma60_pct": 10.42,
      "satisfied_conditions": [
        "현재가_MA60_위",
        "MA60_우상향",
        "종이격_증가중",
        "MACD_영선_위",
        "1D_신고가_발생"
      ],
      "tf_4h": {
        "signal": "STRONG BUY",
        "score": 8,
        "cycle_zone": "2번",
        "cycle_label": "📈 상승가속",
        "jongi_gap": 1.15,
        "macd_signal": "영선위",
        "obv_signal": "상승중",
        "satisfied_conditions": [
          "현재가_MA60_위",
          "MA60_우상향",
          "종이격_증가중",
          "MACD_영선_위",
          "OBV_상승중",
          "거래량_증가",
          "정배열_전환선_10이평_기준선",
          "4H_신고가_발생"
        ],
        "jongi_gaps": [
          0.7166666666666401,
          0.8000000000000114,
          1.0833333333333144,
          1.150000000000034
        ]
      },
      "dual_strong": false
    },
    {
      "symbol": "KRW-ETC",
      "current_price": 12680.0,
      "signal": "WATCH",
      "score": 5,
      "max_score": 9,
      "ma60": 12532.0,
      "jongi_gap": -3.33,
      "jongi_gap_trend": "증가",
      "cycle_zone": "7번",
      "cycle_label": "🔄 하락피크",
      "macd_signal": "영선위",
      "obv_signal": "상승중",
      "volume_signal": "감소",
      "cloud_status": "구름대아래",
      "bb_position": 50.7,
      "price_vs_ma60_pct": 0.06,
      "satisfied_conditions": [
        "현재가_MA60_위",
        "종이격_증가중",
        "MACD_영선_위",
        "OBV_상승중",
        "정배열_전환선_10이평_기준선"
      ],
      "tf_4h": {
        "signal": null,
        "score": null,
        "cycle_zone": null,
        "cycle_label": null,
        "jongi_gap": null,
        "macd_signal": null,
        "obv_signal": null,
        "satisfied_conditions": [],
        "jongi_gaps": []
      },
      "dual_strong": false
    },
    {
      "symbol": "KRW-AKT",
      "current_price": 703.0,
      "signal": "WATCH",
      "score": 5,
      "max_score": 9,
      "ma60": 608.95,
      "jongi_gap": 3.78,
      "jongi_gap_trend": "증가",
      "cycle_zone": "2번",
      "cycle_label": "📈 상승가속",
      "macd_signal": "영선위",
      "obv_signal": "하락중",
      "volume_signal": "감소",
      "cloud_status": "구름대위_양운",
      "bb_position": 28.9,
      "price_vs_ma60_pct": 13.31,
      "satisfied_conditions": [
        "현재가_MA60_위",
        "MA60_우상향",
        "종이격_증가중",
        "MACD_영선_위",
        "구름대_위_및_양운"
      ],
      "tf_4h": {
        "signal": null,
        "score": null,
        "cycle_zone": null,
        "cycle_label": null,
        "jongi_gap": null,
        "macd_signal": null,
        "obv_signal": null,
        "satisfied_conditions": [],
        "jongi_gaps": []
      },
      "dual_strong": false
    },
    {
      "symbol": "KRW-COW",
      "current_price": 323.0,
      "signal": "WATCH",
      "score": 5,
      "max_score": 9,
      "ma60": 318.83,
      "jongi_gap": 1.15,
      "jongi_gap_trend": "증가",
      "cycle_zone": "2번",
      "cycle_label": "📈 상승가속",
      "macd_signal": "영선아래",
      "obv_signal": "상승중",
      "volume_signal": "증가",
      "cloud_status": "구름대아래",
      "bb_position": 74.1,
      "price_vs_ma60_pct": 0.37,
      "satisfied_conditions": [
        "현재가_MA60_위",
        "MA60_우상향",
        "종이격_증가중",
        "OBV_상승중",
        "거래량_증가"
      ],
      "tf_4h": {
        "signal": null,
        "score": null,
        "cycle_zone": null,
        "cycle_label": null,
        "jongi_gap": null,
        "macd_signal": null,
        "obv_signal": null,
        "satisfied_conditions": [],
        "jongi_gaps": []
      },
      "dual_strong": false
    },
    {
      "symbol": "KRW-ARB",
      "current_price": 161.0,
      "signal": "WATCH",
      "score": 5,
      "max_score": 9,
      "ma60": 149.25,
      "jongi_gap": -0.22,
      "jongi_gap_trend": "증가",
      "cycle_zone": "8번",
      "cycle_label": "🌱 바닥권",
      "macd_signal": "영선위",
      "obv_signal": "상승중",
      "volume_signal": "증가",
      "cloud_status": "구름대아래",
      "bb_position": 114.7,
      "price_vs_ma60_pct": 7.2,
      "satisfied_conditions": [
        "현재가_MA60_위",
        "종이격_증가중",
        "MACD_영선_위",
        "OBV_상승중",
        "거래량_증가"
      ],
      "tf_4h": {
        "signal": "STRONG BUY",
        "score": 9,
        "cycle_zone": "2번",
        "cycle_label": "📈 상승가속",
        "jongi_gap": 0.3667,
        "macd_signal": "영선위",
        "obv_signal": "상승중",
        "satisfied_conditions": [
          "현재가_MA60_위",
          "MA60_우상향",
          "종이격_증가중",
          "MACD_영선_위",
          "OBV_상승중",
          "거래량_증가",
          "정배열_전환선_10이평_기준선",
          "구름대_위_및_양운",
          "4H_신고가_발생"
        ],
        "jongi_gaps": [
          0.25,
          0.25,
          0.3499999999999943,
          0.36666666666667425
        ]
      },
      "dual_strong": false
    },
    {
      "symbol": "KRW-AVAX",
      "current_price": 13900.0,
      "signal": "WATCH",
      "score": 5,
      "max_score": 9,
      "ma60": 13633.17,
      "jongi_gap": 7.0,
      "jongi_gap_trend": "증가",
      "cycle_zone": "1번",
      "cycle_label": "🚀 상승전환",
      "macd_signal": "영선아래",
      "obv_signal": "상승중",
      "volume_signal": "증가",
      "cloud_status": "구름대아래",
      "bb_position": 65.2,
      "price_vs_ma60_pct": 1.96,
      "satisfied_conditions": [
        "현재가_MA60_위",
        "MA60_우상향",
        "종이격_증가중",
        "OBV_상승중",
        "거래량_증가"
      ],
      "tf_4h": {
        "signal": null,
        "score": null,
        "cycle_zone": null,
        "cycle_label": null,
        "jongi_gap": null,
        "macd_signal": null,
        "obv_signal": null,
        "satisfied_conditions": [],
        "jongi_gaps": []
      },
      "dual_strong": false
    },
    {
      "symbol": "KRW-SUPER",
      "current_price": 175.0,
      "signal": "WATCH",
      "score": 5,
      "max_score": 9,
      "ma60": 171.37,
      "jongi_gap": -0.12,
      "jongi_gap_trend": "증가",
      "cycle_zone": "7번",
      "cycle_label": "🔄 하락피크",
      "macd_signal": "영선위",
      "obv_signal": "상승중",
      "volume_signal": "증가",
      "cloud_status": "구름대아래",
      "bb_position": 80.4,
      "price_vs_ma60_pct": 3.87,
      "satisfied_conditions": [
        "현재가_MA60_위",
        "종이격_증가중",
        "MACD_영선_위",
        "OBV_상승중",
        "거래량_증가"
      ],
      "tf_4h": {
        "signal": "WATCH",
        "score": 5,
        "cycle_zone": "3번",
        "cycle_label": "⚡ 45도 피크",
        "jongi_gap": 0.25,
        "macd_signal": "영선위",
        "obv_signal": "상승중",
        "satisfied_conditions": [
          "현재가_MA60_위",
          "MA60_우상향",
          "MACD_영선_위",
          "OBV_상승중",
          "정배열_전환선_10이평_기준선"
        ],
        "jongi_gaps": [
          0.3166666666666913,
          0.28333333333333144,
          0.29999999999998295,
          0.25
        ]
      },
      "dual_strong": false
    },
    {
      "symbol": "KRW-QTUM",
      "current_price": 1361.0,
      "signal": "WATCH",
      "score": 5,
      "max_score": 9,
      "ma60": 1350.33,
      "jongi_gap": -0.27,
      "jongi_gap_trend": "증가",
      "cycle_zone": "7번",
      "cycle_label": "🔄 하락피크",
      "macd_signal": "영선위",
      "obv_signal": "상승중",
      "volume_signal": "감소",
      "cloud_status": "구름대아래",
      "bb_position": 57.8,
      "price_vs_ma60_pct": 1.16,
      "satisfied_conditions": [
        "현재가_MA60_위",
        "종이격_증가중",
        "MACD_영선_위",
        "OBV_상승중",
        "정배열_전환선_10이평_기준선"
      ],
      "tf_4h": {
        "signal": null,
        "score": null,
        "cycle_zone": null,
        "cycle_label": null,
        "jongi_gap": null,
        "macd_signal": null,
        "obv_signal": null,
        "satisfied_conditions": [],
        "jongi_gaps": []
      },
      "dual_strong": false
    },
    {
      "symbol": "KRW-LINK",
      "current_price": 13320.0,
      "signal": "WATCH",
      "score": 5,
      "max_score": 9,
      "ma60": 13169.83,
      "jongi_gap": 3.17,
      "jongi_gap_trend": "증가",
      "cycle_zone": "1번",
      "cycle_label": "🚀 상승전환",
      "macd_signal": "영선위",
      "obv_signal": "상승중",
      "volume_signal": "감소",
      "cloud_status": "구름대아래",
      "bb_position": 48.9,
      "price_vs_ma60_pct": 0.91,
      "satisfied_conditions": [
        "현재가_MA60_위",
        "MA60_우상향",
        "종이격_증가중",
        "MACD_영선_위",
        "OBV_상승중"
      ],
      "tf_4h": {
        "signal": null,
        "score": null,
        "cycle_zone": null,
        "cycle_label": null,
        "jongi_gap": null,
        "macd_signal": null,
        "obv_signal": null,
        "satisfied_conditions": [],
        "jongi_gaps": []
      },
      "dual_strong": false
    },
    {
      "symbol": "KRW-PYTH",
      "current_price": 71.4,
      "signal": "WATCH",
      "score": 5,
      "max_score": 9,
      "ma60": 68.92,
      "jongi_gap": 0.05,
      "jongi_gap_trend": "증가",
      "cycle_zone": "1번",
      "cycle_label": "🚀 상승전환",
      "macd_signal": "영선아래",
      "obv_signal": "상승중",
      "volume_signal": "증가",
      "cloud_status": "구름대아래",
      "bb_position": 127.5,
      "price_vs_ma60_pct": 3.01,
      "satisfied_conditions": [
        "현재가_MA60_위",
        "MA60_우상향",
        "종이격_증가중",
        "OBV_상승중",
        "거래량_증가"
      ],
      "tf_4h": {
        "signal": "BUY",
        "score": 6,
        "cycle_zone": "3번",
        "cycle_label": "⚡ 45도 피크",
        "jongi_gap": 0.1517,
        "macd_signal": "영선위",
        "obv_signal": "상승중",
        "satisfied_conditions": [
          "현재가_MA60_위",
          "MA60_우상향",
          "MACD_영선_위",
          "OBV_상승중",
          "거래량_증가",
          "정배열_전환선_10이평_기준선"
        ],
        "jongi_gaps": [
          0.17166666666665975,
          0.19333333333333513,
          0.21666666666666856,
          0.15166666666667084
        ]
      },
      "dual_strong": false
    },
    {
      "symbol": "KRW-RAY",
      "current_price": 941.0,
      "signal": "WATCH",
      "score": 5,
      "max_score": 9,
      "ma60": 907.97,
      "jongi_gap": 0.53,
      "jongi_gap_trend": "증가",
      "cycle_zone": "2번",
      "cycle_label": "📈 상승가속",
      "macd_signal": "영선위",
      "obv_signal": "상승중",
      "volume_signal": "감소",
      "cloud_status": "구름대아래",
      "bb_position": 62.6,
      "price_vs_ma60_pct": 3.2,
      "satisfied_conditions": [
        "현재가_MA60_위",
        "MA60_우상향",
        "종이격_증가중",
        "MACD_영선_위",
        "OBV_상승중"
      ],
      "tf_4h": {
        "signal": null,
        "score": null,
        "cycle_zone": null,
        "cycle_label": null,
        "jongi_gap": null,
        "macd_signal": null,
        "obv_signal": null,
        "satisfied_conditions": [],
        "jongi_gaps": []
      },
      "dual_strong": false
    },
    {
      "symbol": "KRW-COMP",
      "current_price": 29020.0,
      "signal": "WATCH",
      "score": 5,
      "max_score": 9,
      "ma60": 26847.17,
      "jongi_gap": 57.83,
      "jongi_gap_trend": "증가",
      "cycle_zone": "2번",
      "cycle_label": "📈 상승가속",
      "macd_signal": "영선아래",
      "obv_signal": "상승중",
      "volume_signal": "증가",
      "cloud_status": "구름대아래",
      "bb_position": 79.5,
      "price_vs_ma60_pct": 6.9,
      "satisfied_conditions": [
        "현재가_MA60_위",
        "MA60_우상향",
        "종이격_증가중",
        "OBV_상승중",
        "거래량_증가"
      ],
      "tf_4h": {
        "signal": "BUY",
        "score": 7,
        "cycle_zone": "4번",
        "cycle_label": "⚠️ 상승둔화",
        "jongi_gap": 27.6667,
        "macd_signal": "영선위",
        "obv_signal": "상승중",
        "satisfied_conditions": [
          "현재가_MA60_위",
          "MA60_우상향",
          "MACD_영선_위",
          "OBV_상승중",
          "정배열_전환선_10이평_기준선",
          "구름대_위_및_양운",
          "4H_신고가_발생"
        ],
        "jongi_gaps": [
          10.16666666666788,
          37.5,
          36.5,
          27.66666666666424
        ]
      },
      "dual_strong": false
    },
    {
      "symbol": "KRW-RED",
      "current_price": 234.0,
      "signal": "WATCH",
      "score": 5,
      "max_score": 9,
      "ma60": 213.87,
      "jongi_gap": -0.5,
      "jongi_gap_trend": "감소",
      "cycle_zone": "6번",
      "cycle_label": "📉 하락가속",
      "macd_signal": "영선위",
      "obv_signal": "상승중",
      "volume_signal": "증가",
      "cloud_status": "구름대아래",
      "bb_position": 84.8,
      "price_vs_ma60_pct": 17.83,
      "satisfied_conditions": [
        "현재가_MA60_위",
        "MACD_영선_위",
        "OBV_상승중",
        "거래량_증가",
        "정배열_전환선_10이평_기준선"
      ],
      "tf_4h": {
        "signal": null,
        "score": null,
        "cycle_zone": null,
        "cycle_label": null,
        "jongi_gap": null,
        "macd_signal": null,
        "obv_signal": null,
        "satisfied_conditions": [],
        "jongi_gaps": []
      },
      "dual_strong": false
    },
    {
      "symbol": "KRW-STEEM",
      "current_price": 87.1,
      "signal": "WATCH",
      "score": 5,
      "max_score": 9,
      "ma60": 86.04,
      "jongi_gap": 0.19,
      "jongi_gap_trend": "증가",
      "cycle_zone": "2번",
      "cycle_label": "📈 상승가속",
      "macd_signal": "영선아래",
      "obv_signal": "상승중",
      "volume_signal": "감소",
      "cloud_status": "구름대위_양운",
      "bb_position": 29.7,
      "price_vs_ma60_pct": 1.7,
      "satisfied_conditions": [
        "현재가_MA60_위",
        "MA60_우상향",
        "종이격_증가중",
        "OBV_상승중",
        "구름대_위_및_양운"
      ],
      "tf_4h": {
        "signal": null,
        "score": null,
        "cycle_zone": null,
        "cycle_label": null,
        "jongi_gap": null,
        "macd_signal": null,
        "obv_signal": null,
        "satisfied_conditions": [],
        "jongi_gaps": []
      },
      "dual_strong": false
    }
  ],
  "paper_trading": {
    "open_positions": 4,
    "total_trades": 14,
    "win_rate": 10.0,
    "avg_pnl_pct": -5.48,
    "open_list": [
      {
        "symbol": "KRW-RENDER",
        "entry_date": "2026-04-08",
        "entry_price": 3088.0,
        "entry_cycle": "2번",
        "entry_score": 8,
        "dual_strong": true,
        "current_pnl_pct": -1.46
      },
      {
        "symbol": "KRW-JST",
        "entry_date": "2026-04-09",
        "entry_price": 97.6,
        "entry_cycle": "2번",
        "entry_score": 8,
        "dual_strong": false,
        "current_pnl_pct": 6.56
      },
      {
        "symbol": "KRW-SAFE",
        "entry_date": "2026-04-09",
        "entry_price": 182.0,
        "entry_cycle": "2번",
        "entry_score": 8,
        "dual_strong": false,
        "current_pnl_pct": 6.59
      },
      {
        "symbol": "KRW-DKA",
        "entry_date": "2026-04-10",
        "entry_price": 9.02,
        "entry_cycle": "2번",
        "entry_score": 8,
        "dual_strong": false,
        "current_pnl_pct": 0.0
      }
    ]
  }
}